ecs_crd/__init__.py
ecs_crd/applyStrategyStep.py
ecs_crd/canaryReleaseDeployStep.py
ecs_crd/canaryReleaseInfos.py
ecs_crd/cfn_green_release_deploy.json
ecs_crd/cfn_init_release_deploy.json
ecs_crd/cli.py
ecs_crd/createGreenStackStep.py
ecs_crd/createInitStackStep.py
ecs_crd/createStackStep.py
ecs_crd/defaultJSONEncoder.py
ecs_crd/destroyBlueStackStep.py
ecs_crd/destroyGreenStackStep.py
ecs_crd/destroyInitStackStep.py
ecs_crd/destroyStackStep.py
ecs_crd/finishDeploymentStep.py
ecs_crd/prepareDeploymentContainerDefinitionsStep.py
ecs_crd/prepareDeploymentGlobalParametersStep.py
ecs_crd/prepareDeploymentIamPoliciesStep.py
ecs_crd/prepareDeploymentInitStackStep.py
ecs_crd/prepareDeploymentListenersStep.py
ecs_crd/prepareDeploymentLoadBalancerParametersStep.py
ecs_crd/prepareDeploymentScaleParametersStep.py
ecs_crd/prepareDeploymentServiceDefinitionStep.py
ecs_crd/prepareDeploymentStrategyStep.py
ecs_crd/prepareDeploymentTargetGroupsStep.py
ecs_crd/prepareDeploymentTaskDefinitionStep.py
ecs_crd/rollbackChangeRoute53WeightsStep.py
ecs_crd/scaleUpServiceStep.py
ecs_crd/sendNotificationBySnsStep.py
ecs_crd/updateCanaryReleaseInfoStep.py
ecs_crd/versionInfos.py
ecs_crd_cli-1.2.0.data/scripts/ecs-crd
tests/__init__.py
tests/test_prepareDeploymentContainerDefinitionsStep.py
tests/test_prepareDeploymentServiceDefinitionStep.py
ecs_crd_cli-1.2.0.dist-info/LICENSE
ecs_crd_cli-1.2.0.dist-info/METADATA
ecs_crd_cli-1.2.0.dist-info/WHEEL
ecs_crd_cli-1.2.0.dist-info/top_level.txt
ecs_crd_cli-1.2.0.dist-info/RECORD
